agenticos/__init__.py
agenticos/cli/__init__.py
agenticos/cli/cli.py
agenticos/cli/init_agentic.py
agenticos/cli/run_agentic.py
agenticos/cli/templates/agentic_config.py
agenticos/cli/templates/agentic_node.py
agenticos/connectors/__init__.py
agenticos/connectors/base.py
agenticos/connectors/crewai.py
agenticos/node/__init__.py
agenticos/node/http_support.py
agenticos/node/httpnode.py
agenticos/node/models.py
agenticos/node/settings.py
agenticos/node/wsnode.py
agenticos/tools/README.md
agenticos/tools/__init__.py
agenticos/tools/agentic_tools/__init__.py
agenticos/tools/agentic_tools/agentic_tool.py
agenticos/tools/contentful_tool/README.md
agenticos/tools/contentful_tool/__init__.py
agenticos/tools/contentful_tool/contentful_tool.py
agenticos-0.0.3.156507.dist-info/LICENSE
agenticos-0.0.3.156507.dist-info/METADATA
agenticos-0.0.3.156507.dist-info/WHEEL
agenticos-0.0.3.156507.dist-info/entry_points.txt
agenticos-0.0.3.156507.dist-info/RECORD
