Metadata-Version: 2.1
Name: agenticos
Version: 0.0.3.156507
Summary: Tapping into the power of AI agents
Author: Sebastian Kuepers
Author-email: s.kuepers@house-of-communication.com
Requires-Python: >=3.10,<=3.13
Classifier: Programming Language :: Python :: 3
Classifier: Programming Language :: Python :: 3.10
Classifier: Programming Language :: Python :: 3.11
Classifier: Programming Language :: Python :: 3.12
Requires-Dist: agentops (>=0.3.7,<0.4.0)
Requires-Dist: click (>=8.1.7,<9.0.0)
Requires-Dist: fastapi[standard] (>=0.114.2,<0.115.0)
Requires-Dist: pydantic (>=2.0,<3.0)
Requires-Dist: pydantic-settings (>=2.5.2,<3.0.0)
Requires-Dist: requests (>=2.31.0,<3.0.0)
Requires-Dist: tenacity (>=8.1.0,!=8.4.0,<9.0.0)
Requires-Dist: websocket-client (>=1.8.0,<2.0.0)
